cdn_test/__init__.py
cdn_test/cli.py
cdn_test/domain.py
cdn_test-0.1.6.dist-info/entry_points.txt
cdn_test-0.1.6.dist-info/WHEEL
cdn_test-0.1.6.dist-info/METADATA
cdn_test-0.1.6.dist-info/RECORD
