Metadata-Version: 2.1
Name: cdn-test
Version: 0.1.6
Summary: CLI tool to test CDN
Home-page: https://github.com/augustoliks/cdn-test
Keywords: cli,test,cloudfront,aws,cdn
Author: Carlos Neto
Author-email: carlos.neto.dev@gmail.com
Maintainer: Carlos Neto
Maintainer-email: carlos.neto.dev@gmail.com
Requires-Python: >=3.6.1
Classifier: Programming Language :: Python :: 3
Classifier: Programming Language :: Python :: 3.10
Classifier: Programming Language :: Python :: 3.7
Classifier: Programming Language :: Python :: 3.8
Classifier: Programming Language :: Python :: 3.9
Classifier: Topic :: Software Development :: Libraries :: Python Modules
Requires-Dist: pydantic (>=1.8.2,<2.0.0)
Requires-Dist: requests (>=2.26.0,<3.0.0)
Project-URL: Documentation, https://github.com/augustoliks/cdn-test/blob/main/README.rst
